lmfuser_data/__init__.py
lmfuser_data/data_distributor.py
lmfuser_data/data_loader.py
lmfuser_data/data_operators.py
lmfuser_data/interfaces.py
lmfuser_data/row_worker.py
lmfuser_data/utils.py
lmfuser_data/datasets/__init__.py
lmfuser_data/datasets/c4.py
lmfuser_data/scanners/__init__.py
lmfuser_data/scanners/arrow.py
lmfuser_data/scanners/c4.py
lmfuser_data/scanners/interface.py
lmfuser_data/scanners/parquet.py
lmfuser_data-0.1.1.dist-info/METADATA
lmfuser_data-0.1.1.dist-info/WHEEL
lmfuser_data-0.1.1.dist-info/RECORD
