Metadata-Version: 2.4
Name: LMFuser-Data
Version: 0.1.1
Summary: The data accessing and processing infrastructure for LMFuser
Project-URL: Homepage, https://github.com/TYTTYTTYT/LMFuser-data
Project-URL: Bug Tracker, https://github.com/TYTTYTTYT/LMFuser-data
Project-URL: Documentation, https://github.com/TYTTYTTYT/LMFuser-data
Project-URL: Repository, https://github.com/TYTTYTTYT/LMFuser-data
Project-URL: Changelog, https://github.com/TYTTYTTYT/LMFuser-data
Author-email: Yintao Tai <tai.yintao@gmail.com>
Maintainer-email: Yintao Tai <tai.yintao@gmail.com>
Keywords: dataloader,machine learning,parallel,process pool,pytorch,qps
Classifier: Intended Audience :: Information Technology
Classifier: Intended Audience :: Science/Research
Classifier: Programming Language :: Python :: 3 :: Only
Classifier: Topic :: Database
Classifier: Topic :: Database :: Database Engines/Servers
Classifier: Topic :: Utilities
Requires-Python: >=3.10
Requires-Dist: cloudpickle
Requires-Dist: numpy
Requires-Dist: pandas
Requires-Dist: psutil
Requires-Dist: pyarrow
Requires-Dist: requests
Requires-Dist: torch
